tz/__init__.py
tz/main.py
tz/metadata.py
tz/zdump.py
tz-0.2.1.dist-info/DESCRIPTION.rst
tz-0.2.1.dist-info/METADATA
tz-0.2.1.dist-info/RECORD
tz-0.2.1.dist-info/WHEEL
tz-0.2.1.dist-info/entry_points.txt
tz-0.2.1.dist-info/metadata.json
tz-0.2.1.dist-info/top_level.txt
